sqla_utils/__init__.py
sqla_utils/base.py
sqla_utils/builder.py
sqla_utils/exc.py
sqla_utils/py.typed
sqla_utils/session.py
sqla_utils/split_sql.py
sqla_utils/test.py
sqla_utils/transaction.py
sqla_utils/types.py
sqla_utils-0.7.0.dist-info/LICENSE
sqla_utils-0.7.0.dist-info/METADATA
sqla_utils-0.7.0.dist-info/WHEEL
sqla_utils-0.7.0.dist-info/RECORD
