Metadata-Version: 2.3
Name: sqla-utils
Version: 0.7.0
Summary: Opinionated utilities for working with SQLAlchemy
License: MIT
Keywords: sqlalchemy,orm
Author: Sebastian Rittau
Author-email: srittau@rittau.biz
Requires-Python: >= 3.9, < 4
Classifier: Development Status :: 3 - Alpha
Classifier: Intended Audience :: Developers
Classifier: Topic :: Software Development
Classifier: Typing :: Typed
Requires-Dist: SQLAlchemy (>=1.4,<3)
Project-URL: Homepage, https://github.com/srittau/sqla-utils
Project-URL: Repository, https://github.com/srittau/sqla-utils
